simpleconfig/__init__.py
simpleconfig/config.py
simpleconfig/errors.py
smpl_config-1.1.1.dist-info/METADATA
smpl_config-1.1.1.dist-info/WHEEL
smpl_config-1.1.1.dist-info/top_level.txt
smpl_config-1.1.1.dist-info/RECORD
