Metadata-Version: 2.1
Name: smpl-config
Version: 1.1.1
Summary: SimpleConfig module
Author-email: elezor.2009@gmail.com
